hmt/__init__.py
hmt/__main__.py
hmt/config.py
hmt/hmt_types.py
hmt/logger.py
hmt/logging.yaml
hmt/prepare.py
hmt/build/__init__.py
hmt/build/builder.py
hmt/build/json_schema.py
hmt/build/media_types.py
hmt/build/operation.py
hmt/build/param.py
hmt/build/paths.py
hmt/build/result.py
hmt/build/schemadiff.py
hmt/build/servers.py
hmt/build/update_mode.py
hmt/build/writer.py
hmt/serve/__init__.py
hmt/serve/commands.py
hmt/serve/admin/__init__.py
hmt/serve/admin/runner.py
hmt/serve/admin/views.py
hmt/serve/mock/__init__.py
hmt/serve/mock/callbacks.py
hmt/serve/mock/log.py
hmt/serve/mock/matcher.py
hmt/serve/mock/refs.py
hmt/serve/mock/request_processor.py
hmt/serve/mock/request_validation.py
hmt/serve/mock/rest.py
hmt/serve/mock/scope.py
hmt/serve/mock/security.py
hmt/serve/mock/server.py
hmt/serve/mock/specs.py
hmt/serve/mock/views.py
hmt/serve/mock/faker/__init__.py
hmt/serve/mock/faker/faker_base.py
hmt/serve/mock/faker/faker_exception.py
hmt/serve/mock/faker/stateful_faker.py
hmt/serve/mock/faker/stateless_faker.py
hmt/serve/mock/storage/__init__.py
hmt/serve/mock/storage/entity.py
hmt/serve/mock/storage/mock_data.py
hmt/serve/mock/storage/mock_data_store.py
hmt/serve/record/__init__.py
hmt/serve/record/channel.py
hmt/serve/record/proxy.py
hmt/serve/record/proxy_callback.py
hmt/serve/utils/__init__.py
hmt/serve/utils/data_callback.py
hmt/serve/utils/http_utils.py
hmt/serve/utils/opanapi_ext.py
hmt/serve/utils/routing.py
hmt/serve/utils/timers.py
hmt/sinks/__init__.py
hmt/sinks/abstract.py
hmt/sinks/file.py
hmt/sources/__init__.py
hmt/sources/abstract.py
hmt/sources/file.py
hmt/sources/kafka.py
hmt/tutorial/__init__.py
tests/build/__init__.py
tests/build/test_builder.py
tests/build/test_json_schema.py
tests/build/test_paths.py
tests/build/test_query.py
tests/build/test_servers.py
tests/hypo/__init__.py
tests/serve/__init__.py
tests/serve/mock/__init__.py
tests/serve/mock/test_callbacks.py
tests/serve/mock/test_control_via_rest.py
tests/serve/mock/test_matcher.py
hmt-0.3.2.dist-info/LICENSE
hmt-0.3.2.dist-info/METADATA
hmt-0.3.2.dist-info/WHEEL
hmt-0.3.2.dist-info/entry_points.txt
hmt-0.3.2.dist-info/top_level.txt
hmt-0.3.2.dist-info/RECORD
